core/__init__.py
core/commands.py
jalcon-0.1.0.data/scripts/jalcon-admin.py
jalcon-0.1.0.dist-info/LICENSE.txt
jalcon-0.1.0.dist-info/METADATA
jalcon-0.1.0.dist-info/WHEEL
jalcon-0.1.0.dist-info/top_level.txt
jalcon-0.1.0.dist-info/RECORD
