Metadata-Version: 2.1
Name: jalcon
Version: 0.1.0
Summary: jalcon is a bootstrap framework for Falcon with MongoDB
Home-page: https://github.com/jaarce/jalcon
Author: JA Arce
Author-email: johnandrewarce@gmail.com
License: BSD
Keywords: jalcon falcon framework jalcon-rest
Platform: UNKNOWN
Classifier: Topic :: Utilities
Classifier: Environment :: Web Environment
Classifier: License :: OSI Approved :: BSD License
